ModelVisual/__init__.py
Model_Visual-1.1.1.dist-info/LICENSE
Model_Visual-1.1.1.dist-info/METADATA
Model_Visual-1.1.1.dist-info/WHEEL
Model_Visual-1.1.1.dist-info/top_level.txt
Model_Visual-1.1.1.dist-info/RECORD
