Metadata-Version: 2.1
Name: Model-Visual
Version: 1.1.1
Summary: A deep learning model visualization suite based on Mermaid
Home-page: UNKNOWN
Author: YuAn, Lu
Author-email: luyuam0@gmail.com
License: UNKNOWN
Platform: UNKNOWN
Classifier: Programming Language :: Python :: 3
Classifier: License :: OSI Approved :: MIT License
Classifier: Operating System :: OS Independent
Requires-Python: >=3.7
Requires-Dist: tensorflow (>=2.0.0)
